gitupdater/__init__.py
gitupdater/gitupdater.py
gitupdater-1.0.0.dist-info/METADATA
gitupdater-1.0.0.dist-info/WHEEL
gitupdater-1.0.0.dist-info/licenses/LICENSE
gitupdater-1.0.0.dist-info/RECORD
