Metadata-Version: 2.4
Name: gitupdater
Version: 1.0.0
Summary: gitupdater is a lightweight Python git and version management utility package to update tools via GitHub releases using uv, pipx, or pip
Project-URL: Homepage, https://github.com/RevoltSecurities/gitupdater
Project-URL: Documentation, https://github.com/RevoltSecurities/gitupdater
Project-URL: Source, https://github.com/RevoltSecurities/gitupdater
Project-URL: Issues, https://github.com/RevoltSecurities/gitupdater/issues
Author-email: "D. Sanjai Kumar" <bughunterz0047@gmail.com>
License: MIT
License-File: LICENSE
Keywords: auto-update,automation,bugbounty,github,gitupdater,pentesting,pip,pipx,python-tools,security-tools,tooling,uv
Classifier: Development Status :: 5 - Production/Stable
Classifier: Intended Audience :: Developers
Classifier: License :: OSI Approved :: MIT License
Classifier: Operating System :: OS Independent
Classifier: Programming Language :: Python :: 3
Classifier: Programming Language :: Python :: 3.13
Classifier: Topic :: Security
Classifier: Topic :: Software Development :: Libraries :: Python Modules
Classifier: Topic :: System :: Installation/Setup
Classifier: Topic :: System :: Software Distribution
Classifier: Topic :: Utilities
Requires-Python: >=3.13
Requires-Dist: revoltlogger>=1.0.0
Requires-Dist: revoltutils>=1.0.0
Requires-Dist: rich>=14.0.0
